nasaoutgassingjir/__init__.py
nasaoutgassingjir/tmlinfo.py
nasaoutgassingjir-0.0.1.dist-info/LICENSE
nasaoutgassingjir-0.0.1.dist-info/METADATA
nasaoutgassingjir-0.0.1.dist-info/WHEEL
nasaoutgassingjir-0.0.1.dist-info/top_level.txt
nasaoutgassingjir-0.0.1.dist-info/RECORD
