Metadata-Version: 2.1
Name: nasaoutgassingjir
Version: 0.0.1
Summary: print statistics of total mass loss from nasa outgassing db
Home-page: https://github.com/juanitoetc
Author: Juan Ignacio Robledo
Author-email: juanignacio.robledo@gmail.com
License: UNKNOWN
Project-URL: Bug Tracker, https://github.com/juanitoetc/nasa-outgassing-tml/issues
Platform: UNKNOWN
Classifier: Programming Language :: Python :: 3
Classifier: License :: OSI Approved :: MIT License
Classifier: Operating System :: OS Independent
Requires-Python: >=3.6
License-File: LICENSE
